fits2rgb/__init__.py
fits2rgb/_version.py
fits2rgb/core.py
fits2rgb-0.2.1.dist-info/LICENSE
fits2rgb-0.2.1.dist-info/METADATA
fits2rgb-0.2.1.dist-info/WHEEL
fits2rgb-0.2.1.dist-info/entry_points.txt
fits2rgb-0.2.1.dist-info/top_level.txt
fits2rgb-0.2.1.dist-info/RECORD
