Metadata-Version: 2.1
Name: fits2rgb
Version: 0.2.1
Summary: Merge multiple FITS images into a single FITS RGB file.
Author: Maurizio D'Addona
Author-email: mauritiusdadd@gmail.com
Maintainer: Maurizio D'Addona
Maintainer-email: mauritiusdadd@gmail.com
License: BSD 3-Clause License
Project-URL: repository, https://github.com/mauritiusdadd/fits2rgb
Keywords: imaging,FITS,astronomy
Classifier: Development Status :: 4 - Beta
Classifier: Intended Audience :: Science/Research
Classifier: Topic :: Multimedia :: Graphics :: Graphics Conversion
Classifier: Programming Language :: Python :: 3
Requires-Python: >=3.8
License-File: LICENSE
Requires-Dist: numpy
Requires-Dist: scipy
Requires-Dist: astropy
Requires-Dist: reproject
Provides-Extra: test
Requires-Dist: pytest ; extra == 'test'
Requires-Dist: tqdm ; extra == 'test'
